project_python_203/Data_treatment.py
project_python_203/Trades.py
project_python_203/__init__.py
project_python_203/project_python_203.py
project_python_203-0.4.1.dist-info/LICENSE
project_python_203-0.4.1.dist-info/METADATA
project_python_203-0.4.1.dist-info/WHEEL
project_python_203-0.4.1.dist-info/RECORD
